Metadata-Version: 1.0
Name: jujube
Version: 0.0.1
Summary: 我了个去
Home-page: https://github.com/yuejing08/hello
Author: yuejing08
Author-email: 568623642@qq.com
License: UNKNOWN
Platform: UNKNOWN
